vernissage/cli.py
vernissage/functions.py
vernissage-0.2.1.dist-info/METADATA
vernissage-0.2.1.dist-info/WHEEL
vernissage-0.2.1.dist-info/entry_points.txt
vernissage-0.2.1.dist-info/RECORD
